satseg/__init__.py
satseg/dataset.py
satseg/geo_tools.py
satseg/grid_optim.py
satseg/model.py
satseg/seg_result.py
satseg/utils.py
satseg-0.1.1.dist-info/METADATA
satseg-0.1.1.dist-info/WHEEL
satseg-0.1.1.dist-info/RECORD
