Metadata-Version: 2.1
Name: satseg
Version: 0.1.1
Summary: A python package to assist in multispectral satellite image segmentation.
Author: Dilith Jayakody
Author-email: dilithjay@gmail.com
Requires-Python: >=3.8,<4.0
Classifier: Programming Language :: Python :: 3
Classifier: Programming Language :: Python :: 3.8
Classifier: Programming Language :: Python :: 3.9
Classifier: Programming Language :: Python :: 3.10
Classifier: Programming Language :: Python :: 3.11
Requires-Dist: geopandas (>=0.12.2,<0.13.0)
Requires-Dist: numpy (>=1.24.2,<2.0.0)
Requires-Dist: opencv-python (>=4.7.0.72,<5.0.0.0)
Requires-Dist: pandas (>=2.0.0,<3.0.0)
Requires-Dist: rasterio (>=1.3.6,<2.0.0)
Requires-Dist: segmentation-models-pytorch (>=0.3.2,<0.4.0)
Requires-Dist: torch (>=2.0.0,<3.0.0)
Requires-Dist: torchgeo (>=0.4.1,<0.5.0)
Requires-Dist: torchvision (>=0.15.1,<0.16.0)
